sanickit/__about__.py
sanickit/__init__.py
sanickit/cli.py
sanickit/code.py
sanickit/console.css
sanickit/console.py
sanickit/template/__init__.py
sanickit/template/server.py
sanickit/template/default/README.md.jinja
sanickit/template/default/src/+head.html
sanickit/template/default/src/index.html
sanickit/template/default/src/server_setup.py
sanickit/template/default/src/blueprints/.gitkeep
sanickit/template/default/src/lib/.gitkeep
sanickit/template/default/src/middleware/htmx.py
sanickit/template/default/src/routes/+layout.html
sanickit/template/default/src/routes/+page.sanic
sanickit/template/default/static/app.css
sanickit-0.0.6.dist-info/METADATA
sanickit-0.0.6.dist-info/WHEEL
sanickit-0.0.6.dist-info/entry_points.txt
sanickit-0.0.6.dist-info/licenses/LICENSE
sanickit-0.0.6.dist-info/RECORD
