Metadata-Version: 2.1
Name: sanickit
Version: 0.0.6
Summary: A web framework that applies some of the ideas of SvelteKit to Sanic
Project-URL: Documentation, https://github.com/lllama/sanickit#readme
Project-URL: Issues, https://github.com/lllama/sanickit/issues
Project-URL: Source, https://github.com/lllama/sanickit
Author-email: Felix Ingram <f.ingram@gmail.com>
License-Expression: MIT
License-File: LICENSE
Classifier: Development Status :: 4 - Beta
Classifier: Programming Language :: Python
Classifier: Programming Language :: Python :: 3.7
Classifier: Programming Language :: Python :: 3.8
Classifier: Programming Language :: Python :: 3.9
Classifier: Programming Language :: Python :: 3.10
Classifier: Programming Language :: Python :: 3.11
Classifier: Programming Language :: Python :: Implementation :: CPython
Classifier: Programming Language :: Python :: Implementation :: PyPy
Requires-Python: >=3.10
Requires-Dist: beautifulsoup4
Requires-Dist: click
Requires-Dist: copier
Requires-Dist: httpx
Requires-Dist: jinja2
Requires-Dist: jinja2-fragments
Requires-Dist: rich
Requires-Dist: sanic
Requires-Dist: sanic-ext
Requires-Dist: textual
Requires-Dist: tomlkit
Requires-Dist: watchfiles
